{"verbs": [{"verb": "said", "description": "[ARG0: A source close to the president] [V: said] [ARG1: Trump \" Does . Not . Care . His whole adult life has been spent in litigation . He 's not afraid of high - stakes legal stuff] . \u2026 [ARG0: He]", "tags": ["B-ARG0", "I-ARG0", "I-ARG0", "I-ARG0", "I-ARG0", "I-ARG0", "B-V", "B-ARG1", "I-ARG1", "I-ARG1", "I-ARG1", "I-ARG1", "I-ARG1", "I-ARG1", "I-ARG1", "I-ARG1", "I-ARG1", "I-ARG1", "I-ARG1", "I-ARG1", "I-ARG1", "I-ARG1", "I-ARG1", "I-ARG1", "I-ARG1", "I-ARG1", "I-ARG1", "I-ARG1", "I-ARG1", "I-ARG1", "I-ARG1", "I-ARG1", "I-ARG1", "I-ARG1", "I-ARG1", "O", "O", "B-ARG0"]}, {"verb": "Does", "description": "A source close to the president said Trump \" [V: Does] . Not . Care . His whole adult life has been spent in litigation . He 's not afraid of high - stakes legal stuff . \u2026 He", "tags": ["O", "O", "O", "O", "O", "O", "O", "O", "O", "B-V", "O", "O", "O", "O", "O", "O", "O", "O", "O", "O", "O", "O", "O", "O", "O", "O", "O", "O", "O", "O", "O", "O", "O", "O", "O", "O", "O", "O"]}, {"verb": "has", "description": "A source close to the president said Trump \" Does . Not . Care . His whole adult life [V: has] been spent in litigation . He 's not afraid of high - stakes legal stuff . \u2026 He", "tags": ["O", "O", "O", "O", "O", "O", "O", "O", "O", "O", "O", "O", "O", "O", "O", "O", "O", "O", "O", "B-V", "O", "O", "O", "O", "O", "O", "O", "O", "O", "O", "O", "O", "O", "O", "O", "O", "O", "O"]}, {"verb": "been", "description": "A source close to the president said Trump \" Does . Not . Care . His whole adult life has [V: been] spent in litigation . He 's not afraid of high - stakes legal stuff . \u2026 He", "tags": ["O", "O", "O", "O", "O", "O", "O", "O", "O", "O", "O", "O", "O", "O", "O", "O", "O", "O", "O", "O", "B-V", "O", "O", "O", "O", "O", "O", "O", "O", "O", "O", "O", "O", "O", "O", "O", "O", "O"]}, {"verb": "spent", "description": "A source close to the president said Trump \" Does . Not . Care . [ARG1: His whole adult life] has been [V: spent] [ARG2: in litigation] . He 's not afraid of high - stakes legal stuff . \u2026 He", "tags": ["O", "O", "O", "O", "O", "O", "O", "O", "O", "O", "O", "O", "O", "O", "O", "B-ARG1", "I-ARG1", "I-ARG1", "I-ARG1", "O", "O", "B-V", "B-ARG2", "I-ARG2", "O", "O", "O", "O", "O", "O", "O", "O", "O", "O", "O", "O", "O", "O"]}, {"verb": "'s", "description": "A source close to the president said Trump \" Does . Not . Care . His whole adult life has been spent in litigation . [ARG1: He] [V: 's] [ARGM-NEG: not] [ARG2: afraid of high - stakes legal stuff] . \u2026 He", "tags": ["O", "O", "O", "O", "O", "O", "O", "O", "O", "O", "O", "O", "O", "O", "O", "O", "O", "O", "O", "O", "O", "O", "O", "O", "O", "B-ARG1", "B-V", "B-ARGM-NEG", "B-ARG2", "I-ARG2", "I-ARG2", "I-ARG2", "I-ARG2", "I-ARG2", "I-ARG2", "O", "O", "O"]}], "words": ["A", "source", "close", "to", "the", "president", "said", "Trump", "\"", "Does", ".", "Not", ".", "Care", ".", "His", "whole", "adult", "life", "has", "been", "spent", "in", "litigation", ".", "He", "'s", "not", "afraid", "of", "high", "-", "stakes", "legal", "stuff", ".", "\u2026", "He"]}