{"verbs": [{"verb": "gets", "description": "\u2018 [ARG0: Kanye West] [V: gets] [ARG1: it] \u2014 when he sees African American unemployment is the lowest in history , you know , people are watching,\u2019President Trump told a crowd in Michigan on Saturday .", "tags": ["O", "B-ARG0", "I-ARG0", "B-V", "B-ARG1", "O", "O", "O", "O", "O", "O", "O", "O", "O", "O", "O", "O", "O", "O", "O", "O", "O", "O", "O", "O", "O", "O", "O", "O", "O", "O", "O", "O"]}, {"verb": "sees", "description": "\u2018 Kanye West gets it \u2014 [ARGM-TMP: when] [ARG0: he] [V: sees] [ARG1: African American unemployment is the lowest in history] , you know , people are watching,\u2019President Trump told a crowd in Michigan on Saturday .", "tags": ["O", "O", "O", "O", "O", "O", "B-ARGM-TMP", "B-ARG0", "B-V", "B-ARG1", "I-ARG1", "I-ARG1", "I-ARG1", "I-ARG1", "I-ARG1", "I-ARG1", "I-ARG1", "O", "O", "O", "O", "O", "O", "O", "O", "O", "O", "O", "O", "O", "O", "O", "O"]}, {"verb": "is", "description": "\u2018 Kanye West gets it \u2014 when he sees [ARG1: African American unemployment] [V: is] [ARG2: the lowest in history] , you know , people are watching,\u2019President Trump told a crowd in Michigan on Saturday .", "tags": ["O", "O", "O", "O", "O", "O", "O", "O", "O", "B-ARG1", "I-ARG1", "I-ARG1", "B-V", "B-ARG2", "I-ARG2", "I-ARG2", "I-ARG2", "O", "O", "O", "O", "O", "O", "O", "O", "O", "O", "O", "O", "O", "O", "O", "O"]}, {"verb": "know", "description": "\u2018 Kanye West gets it \u2014 when he sees African American unemployment is the lowest in history , [ARG0: you] [V: know] , people are watching,\u2019President Trump told a crowd in Michigan on Saturday .", "tags": ["O", "O", "O", "O", "O", "O", "O", "O", "O", "O", "O", "O", "O", "O", "O", "O", "O", "O", "B-ARG0", "B-V", "O", "O", "O", "O", "O", "O", "O", "O", "O", "O", "O", "O", "O"]}, {"verb": "are", "description": "\u2018 Kanye West gets it \u2014 when he sees African American unemployment is the lowest in history , you know , people [V: are] watching,\u2019President Trump told a crowd in Michigan on Saturday .", "tags": ["O", "O", "O", "O", "O", "O", "O", "O", "O", "O", "O", "O", "O", "O", "O", "O", "O", "O", "O", "O", "O", "O", "B-V", "O", "O", "O", "O", "O", "O", "O", "O", "O", "O"]}, {"verb": "told", "description": "\u2018 Kanye West gets it \u2014 when he sees African American unemployment is the lowest in history , you know , people are watching,\u2019President [ARG0: Trump] [V: told] [ARG2: a crowd in Michigan] [ARGM-TMP: on Saturday] .", "tags": ["O", "O", "O", "O", "O", "O", "O", "O", "O", "O", "O", "O", "O", "O", "O", "O", "O", "O", "O", "O", "O", "O", "O", "O", "B-ARG0", "B-V", "B-ARG2", "I-ARG2", "I-ARG2", "I-ARG2", "B-ARGM-TMP", "I-ARGM-TMP", "O"]}], "words": ["\u2018", "Kanye", "West", "gets", "it", "\u2014", "when", "he", "sees", "African", "American", "unemployment", "is", "the", "lowest", "in", "history", ",", "you", "know", ",", "people", "are", "watching,\u2019President", "Trump", "told", "a", "crowd", "in", "Michigan", "on", "Saturday", "."]}