{"verbs": [{"verb": "are", "description": "Senators Ted Cruz and Lamar Alexander [V: are] polling their GOP colleagues for ideas as Leader Mitch McConnell resists ' messaging ' votes and President Trump dominates agenda", "tags": ["O", "O", "O", "O", "O", "O", "B-V", "O", "O", "O", "O", "O", "O", "O", "O", "O", "O", "O", "O", "O", "O", "O", "O", "O", "O", "O", "O"]}, {"verb": "polling", "description": "[ARG0: Senators Ted Cruz and Lamar Alexander] are [V: polling] [ARG1: their GOP colleagues] [ARG2: for ideas] [ARGM-TMP: as Leader Mitch McConnell resists ' messaging ' votes and President Trump dominates agenda]", "tags": ["B-ARG0", "I-ARG0", "I-ARG0", "I-ARG0", "I-ARG0", "I-ARG0", "O", "B-V", "B-ARG1", "I-ARG1", "I-ARG1", "B-ARG2", "I-ARG2", "B-ARGM-TMP", "I-ARGM-TMP", "I-ARGM-TMP", "I-ARGM-TMP", "I-ARGM-TMP", "I-ARGM-TMP", "I-ARGM-TMP", "I-ARGM-TMP", "I-ARGM-TMP", "I-ARGM-TMP", "I-ARGM-TMP", "I-ARGM-TMP", "I-ARGM-TMP", "I-ARGM-TMP"]}, {"verb": "resists", "description": "Senators Ted Cruz and Lamar Alexander are polling their GOP colleagues for ideas as [ARG0: Leader Mitch McConnell] [V: resists] [ARG1: ' messaging ' votes] and President Trump dominates agenda", "tags": ["O", "O", "O", "O", "O", "O", "O", "O", "O", "O", "O", "O", "O", "O", "B-ARG0", "I-ARG0", "I-ARG0", "B-V", "B-ARG1", "I-ARG1", "I-ARG1", "I-ARG1", "O", "O", "O", "O", "O"]}, {"verb": "messaging", "description": "Senators Ted Cruz and Lamar Alexander are polling their GOP colleagues for ideas as Leader Mitch McConnell resists ' [V: messaging] ' [ARG1: votes] and President Trump dominates agenda", "tags": ["O", "O", "O", "O", "O", "O", "O", "O", "O", "O", "O", "O", "O", "O", "O", "O", "O", "O", "O", "B-V", "O", "B-ARG1", "O", "O", "O", "O", "O"]}, {"verb": "dominates", "description": "Senators Ted Cruz and Lamar Alexander are polling their GOP colleagues for ideas as Leader Mitch McConnell resists ' messaging ' votes and [ARG0: President Trump] [V: dominates] [ARG1: agenda]", "tags": ["O", "O", "O", "O", "O", "O", "O", "O", "O", "O", "O", "O", "O", "O", "O", "O", "O", "O", "O", "O", "O", "O", "O", "B-ARG0", "I-ARG0", "B-V", "B-ARG1"]}], "words": ["Senators", "Ted", "Cruz", "and", "Lamar", "Alexander", "are", "polling", "their", "GOP", "colleagues", "for", "ideas", "as", "Leader", "Mitch", "McConnell", "resists", "'", "messaging", "'", "votes", "and", "President", "Trump", "dominates", "agenda"]}