{"verbs": [{"verb": "marked", "description": "[ARG0: President Trump] [ARGM-TMP: on Thursday] [V: marked] [ARG1: the one year anniversary of Special Counsel Robert Mueller 's investigation into the Russian election interference with a tweet \" congratulating America \" for \" the greatest Witch Hunt in American History] . \"", "tags": ["B-ARG0", "I-ARG0", "B-ARGM-TMP", "I-ARGM-TMP", "B-V", "B-ARG1", "I-ARG1", "I-ARG1", "I-ARG1", "I-ARG1", "I-ARG1", "I-ARG1", "I-ARG1", "I-ARG1", "I-ARG1", "I-ARG1", "I-ARG1", "I-ARG1", "I-ARG1", "I-ARG1", "I-ARG1", "I-ARG1", "I-ARG1", "I-ARG1", "I-ARG1", "I-ARG1", "I-ARG1", "I-ARG1", "I-ARG1", "I-ARG1", "I-ARG1", "I-ARG1", "I-ARG1", "I-ARG1", "I-ARG1", "I-ARG1", "I-ARG1", "O", "O"]}, {"verb": "congratulating", "description": "President Trump on Thursday marked the one year anniversary of Special Counsel Robert Mueller 's investigation into the Russian election interference with [ARG0: a tweet] \" [V: congratulating] [ARG1: America] \" [ARG2: for \" the greatest Witch Hunt in American History] . \"", "tags": ["O", "O", "O", "O", "O", "O", "O", "O", "O", "O", "O", "O", "O", "O", "O", "O", "O", "O", "O", "O", "O", "O", "B-ARG0", "I-ARG0", "O", "B-V", "B-ARG1", "O", "B-ARG2", "I-ARG2", "I-ARG2", "I-ARG2", "I-ARG2", "I-ARG2", "I-ARG2", "I-ARG2", "I-ARG2", "O", "O"]}], "words": ["President", "Trump", "on", "Thursday", "marked", "the", "one", "year", "anniversary", "of", "Special", "Counsel", "Robert", "Mueller", "'s", "investigation", "into", "the", "Russian", "election", "interference", "with", "a", "tweet", "\"", "congratulating", "America", "\"", "for", "\"", "the", "greatest", "Witch", "Hunt", "in", "American", "History", ".", "\""]}