{"verbs": [{"verb": "says", "description": "[ARG0: Trump] [V: says] [ARG1: he opposes any immigration legislation that does n\u2019t include \u201c a real wall \u201d along the Mexican border]", "tags": ["B-ARG0", "B-V", "B-ARG1", "I-ARG1", "I-ARG1", "I-ARG1", "I-ARG1", "I-ARG1", "I-ARG1", "I-ARG1", "I-ARG1", "I-ARG1", "I-ARG1", "I-ARG1", "I-ARG1", "I-ARG1", "I-ARG1", "I-ARG1", "I-ARG1", "I-ARG1"]}, {"verb": "opposes", "description": "Trump says [ARG0: he] [V: opposes] [ARG1: any immigration legislation that does n\u2019t include \u201c a real wall \u201d along the Mexican border]", "tags": ["O", "O", "B-ARG0", "B-V", "B-ARG1", "I-ARG1", "I-ARG1", "I-ARG1", "I-ARG1", "I-ARG1", "I-ARG1", "I-ARG1", "I-ARG1", "I-ARG1", "I-ARG1", "I-ARG1", "I-ARG1", "I-ARG1", "I-ARG1", "I-ARG1"]}, {"verb": "does", "description": "Trump says he opposes any immigration legislation that [V: does] n\u2019t include \u201c a real wall \u201d along the Mexican border", "tags": ["O", "O", "O", "O", "O", "O", "O", "O", "B-V", "O", "O", "O", "O", "O", "O", "O", "O", "O", "O", "O"]}, {"verb": "include", "description": "Trump says he opposes [ARG2: any immigration legislation] [R-ARG2: that] does [ARGM-NEG: n\u2019t] [V: include] [ARG1: \u201c a real wall \u201d along the Mexican border]", "tags": ["O", "O", "O", "O", "B-ARG2", "I-ARG2", "I-ARG2", "B-R-ARG2", "O", "B-ARGM-NEG", "B-V", "B-ARG1", "I-ARG1", "I-ARG1", "I-ARG1", "I-ARG1", "I-ARG1", "I-ARG1", "I-ARG1", "I-ARG1"]}], "words": ["Trump", "says", "he", "opposes", "any", "immigration", "legislation", "that", "does", "n\u2019t", "include", "\u201c", "a", "real", "wall", "\u201d", "along", "the", "Mexican", "border"]}