{"verbs": [{"verb": "was", "description": "For some reason , the president \u2019s lawyer Emmet T. Flood [V: was] invited to an intelligence briefing on the role an FBI informant played in the probe into Trump \u2019s campaign .", "tags": ["O", "O", "O", "O", "O", "O", "O", "O", "O", "O", "O", "B-V", "O", "O", "O", "O", "O", "O", "O", "O", "O", "O", "O", "O", "O", "O", "O", "O", "O", "O", "O", "O"]}, {"verb": "invited", "description": "[ARGM-CAU: For some reason] , [ARG1: the president \u2019s lawyer Emmet T. Flood] was [V: invited] [ARG2: to an intelligence briefing on the role an FBI informant played in the probe into Trump \u2019s campaign] .", "tags": ["B-ARGM-CAU", "I-ARGM-CAU", "I-ARGM-CAU", "O", "B-ARG1", "I-ARG1", "I-ARG1", "I-ARG1", "I-ARG1", "I-ARG1", "I-ARG1", "O", "B-V", "B-ARG2", "I-ARG2", "I-ARG2", "I-ARG2", "I-ARG2", "I-ARG2", "I-ARG2", "I-ARG2", "I-ARG2", "I-ARG2", "I-ARG2", "I-ARG2", "I-ARG2", "I-ARG2", "I-ARG2", "I-ARG2", "I-ARG2", "I-ARG2", "O"]}, {"verb": "played", "description": "For some reason , the president \u2019s lawyer Emmet T. Flood was invited to an intelligence briefing on [ARG1: the role] [ARG0: an FBI informant] [V: played] [ARGM-LOC: in the probe into Trump \u2019s campaign] .", "tags": ["O", "O", "O", "O", "O", "O", "O", "O", "O", "O", "O", "O", "O", "O", "O", "O", "O", "O", "B-ARG1", "I-ARG1", "B-ARG0", "I-ARG0", "I-ARG0", "B-V", "B-ARGM-LOC", "I-ARGM-LOC", "I-ARGM-LOC", "I-ARGM-LOC", "I-ARGM-LOC", "I-ARGM-LOC", "I-ARGM-LOC", "O"]}], "words": ["For", "some", "reason", ",", "the", "president", "\u2019s", "lawyer", "Emmet", "T.", "Flood", "was", "invited", "to", "an", "intelligence", "briefing", "on", "the", "role", "an", "FBI", "informant", "played", "in", "the", "probe", "into", "Trump", "\u2019s", "campaign", "."]}