{"verbs": [{"verb": "had", "description": "[ARG0: U.S. Rep. Martha Roby] [V: had] [ARG1: four challengers] [ARGM-LOC: in the Republican primary] , and was attacked for being insufficiently loyal to President Donald Trump . She will face Bobby Bright in a runoff .", "tags": ["B-ARG0", "I-ARG0", "I-ARG0", "I-ARG0", "B-V", "B-ARG1", "I-ARG1", "B-ARGM-LOC", "I-ARGM-LOC", "I-ARGM-LOC", "I-ARGM-LOC", "O", "O", "O", "O", "O", "O", "O", "O", "O", "O", "O", "O", "O", "O", "O", "O", "O", "O", "O", "O", "O", "O"]}, {"verb": "was", "description": "U.S. Rep. Martha Roby had four challengers in the Republican primary , and [V: was] attacked for being insufficiently loyal to President Donald Trump . She will face Bobby Bright in a runoff .", "tags": ["O", "O", "O", "O", "O", "O", "O", "O", "O", "O", "O", "O", "O", "B-V", "O", "O", "O", "O", "O", "O", "O", "O", "O", "O", "O", "O", "O", "O", "O", "O", "O", "O", "O"]}, {"verb": "attacked", "description": "[ARG1: U.S. Rep. Martha Roby] had four challengers in the Republican primary , and was [V: attacked] [ARG2: for being insufficiently loyal to President Donald Trump] . She will face Bobby Bright in a runoff .", "tags": ["B-ARG1", "I-ARG1", "I-ARG1", "I-ARG1", "O", "O", "O", "O", "O", "O", "O", "O", "O", "O", "B-V", "B-ARG2", "I-ARG2", "I-ARG2", "I-ARG2", "I-ARG2", "I-ARG2", "I-ARG2", "I-ARG2", "O", "O", "O", "O", "O", "O", "O", "O", "O", "O"]}, {"verb": "being", "description": "[ARG1: U.S. Rep. Martha Roby] had four challengers in the Republican primary , and was attacked for [V: being] [ARG2: insufficiently loyal to President Donald Trump] . She will face Bobby Bright in a runoff .", "tags": ["B-ARG1", "I-ARG1", "I-ARG1", "I-ARG1", "O", "O", "O", "O", "O", "O", "O", "O", "O", "O", "O", "O", "B-V", "B-ARG2", "I-ARG2", "I-ARG2", "I-ARG2", "I-ARG2", "I-ARG2", "O", "O", "O", "O", "O", "O", "O", "O", "O", "O"]}, {"verb": "will", "description": "U.S. Rep. Martha Roby had four challengers in the Republican primary , and was attacked for being insufficiently loyal to President Donald Trump . She [V: will] face Bobby Bright in a runoff .", "tags": ["O", "O", "O", "O", "O", "O", "O", "O", "O", "O", "O", "O", "O", "O", "O", "O", "O", "O", "O", "O", "O", "O", "O", "O", "O", "B-V", "O", "O", "O", "O", "O", "O", "O"]}, {"verb": "face", "description": "U.S. Rep. Martha Roby had four challengers in the Republican primary , and was attacked for being insufficiently loyal to President Donald Trump . [ARG0: She] [ARGM-MOD: will] [V: face] [ARG1: Bobby Bright] [ARGM-LOC: in a runoff] .", "tags": ["O", "O", "O", "O", "O", "O", "O", "O", "O", "O", "O", "O", "O", "O", "O", "O", "O", "O", "O", "O", "O", "O", "O", "O", "B-ARG0", "B-ARGM-MOD", "B-V", "B-ARG1", "I-ARG1", "B-ARGM-LOC", "I-ARGM-LOC", "I-ARGM-LOC", "O"]}], "words": ["U.S.", "Rep.", "Martha", "Roby", "had", "four", "challengers", "in", "the", "Republican", "primary", ",", "and", "was", "attacked", "for", "being", "insufficiently", "loyal", "to", "President", "Donald", "Trump", ".", "She", "will", "face", "Bobby", "Bright", "in", "a", "runoff", "."]}