{"verbs": [{"verb": "got", "description": "[ARG1: Donald Trump \u2019s fee fees] [V: got] [ARG2: hurt] [ARGM-TMP: after the Philadelphia Eagles informed him that only a few representatives of the club would be coming to the White House to meet him . Trump processed this information maturely and decided to publicly un - invite the] ...", "tags": ["B-ARG1", "I-ARG1", "I-ARG1", "I-ARG1", "I-ARG1", "B-V", "B-ARG2", "B-ARGM-TMP", "I-ARGM-TMP", "I-ARGM-TMP", "I-ARGM-TMP", "I-ARGM-TMP", "I-ARGM-TMP", "I-ARGM-TMP", "I-ARGM-TMP", "I-ARGM-TMP", "I-ARGM-TMP", "I-ARGM-TMP", "I-ARGM-TMP", "I-ARGM-TMP", "I-ARGM-TMP", "I-ARGM-TMP", "I-ARGM-TMP", "I-ARGM-TMP", "I-ARGM-TMP", "I-ARGM-TMP", "I-ARGM-TMP", "I-ARGM-TMP", "I-ARGM-TMP", "I-ARGM-TMP", "I-ARGM-TMP", "I-ARGM-TMP", "I-ARGM-TMP", "I-ARGM-TMP", "I-ARGM-TMP", "I-ARGM-TMP", "I-ARGM-TMP", "I-ARGM-TMP", "I-ARGM-TMP", "I-ARGM-TMP", "I-ARGM-TMP", "I-ARGM-TMP", "I-ARGM-TMP", "I-ARGM-TMP", "I-ARGM-TMP", "O"]}, {"verb": "hurt", "description": "[ARG1: Donald Trump \u2019s fee fees] got [V: hurt] [ARGM-TMP: after the Philadelphia Eagles informed him that only a few representatives of the club would be coming to the White House to meet him . Trump processed this information maturely and decided to publicly un - invite the] ...", "tags": ["B-ARG1", "I-ARG1", "I-ARG1", "I-ARG1", "I-ARG1", "O", "B-V", "B-ARGM-TMP", "I-ARGM-TMP", "I-ARGM-TMP", "I-ARGM-TMP", "I-ARGM-TMP", "I-ARGM-TMP", "I-ARGM-TMP", "I-ARGM-TMP", "I-ARGM-TMP", "I-ARGM-TMP", "I-ARGM-TMP", "I-ARGM-TMP", "I-ARGM-TMP", "I-ARGM-TMP", "I-ARGM-TMP", "I-ARGM-TMP", "I-ARGM-TMP", "I-ARGM-TMP", "I-ARGM-TMP", "I-ARGM-TMP", "I-ARGM-TMP", "I-ARGM-TMP", "I-ARGM-TMP", "I-ARGM-TMP", "I-ARGM-TMP", "I-ARGM-TMP", "I-ARGM-TMP", "I-ARGM-TMP", "I-ARGM-TMP", "I-ARGM-TMP", "I-ARGM-TMP", "I-ARGM-TMP", "I-ARGM-TMP", "I-ARGM-TMP", "I-ARGM-TMP", "I-ARGM-TMP", "I-ARGM-TMP", "I-ARGM-TMP", "O"]}, {"verb": "informed", "description": "Donald Trump \u2019s fee fees got hurt after [ARG0: the Philadelphia Eagles] [V: informed] [ARG1: him] [ARG2: that only a few representatives of the club would be coming to the White House to meet him] . Trump processed this information maturely and decided to publicly un - invite the ...", "tags": ["O", "O", "O", "O", "O", "O", "O", "O", "B-ARG0", "I-ARG0", "I-ARG0", "B-V", "B-ARG1", "B-ARG2", "I-ARG2", "I-ARG2", "I-ARG2", "I-ARG2", "I-ARG2", "I-ARG2", "I-ARG2", "I-ARG2", "I-ARG2", "I-ARG2", "I-ARG2", "I-ARG2", "I-ARG2", "I-ARG2", "I-ARG2", "I-ARG2", "I-ARG2", "O", "O", "O", "O", "O", "O", "O", "O", "O", "O", "O", "O", "O", "O", "O"]}, {"verb": "would", "description": "Donald Trump \u2019s fee fees got hurt after the Philadelphia Eagles informed him that only a few representatives of the club [V: would] be coming to the White House to meet him . Trump processed this information maturely and decided to publicly un - invite the ...", "tags": ["O", "O", "O", "O", "O", "O", "O", "O", "O", "O", "O", "O", "O", "O", "O", "O", "O", "O", "O", "O", "O", "B-V", "O", "O", "O", "O", "O", "O", "O", "O", "O", "O", "O", "O", "O", "O", "O", "O", "O", "O", "O", "O", "O", "O", "O", "O"]}, {"verb": "be", "description": "Donald Trump \u2019s fee fees got hurt after the Philadelphia Eagles informed him that only a few representatives of the club would [V: be] coming to the White House to meet him . Trump processed this information maturely and decided to publicly un - invite the ...", "tags": ["O", "O", "O", "O", "O", "O", "O", "O", "O", "O", "O", "O", "O", "O", "O", "O", "O", "O", "O", "O", "O", "O", "B-V", "O", "O", "O", "O", "O", "O", "O", "O", "O", "O", "O", "O", "O", "O", "O", "O", "O", "O", "O", "O", "O", "O", "O"]}, {"verb": "coming", "description": "Donald Trump \u2019s fee fees got hurt after the Philadelphia Eagles informed him that [ARG1: only a few representatives of the club] [ARGM-MOD: would] be [V: coming] [ARG4: to the White House] [ARGM-PRP: to meet him] . Trump processed this information maturely and decided to publicly un - invite the ...", "tags": ["O", "O", "O", "O", "O", "O", "O", "O", "O", "O", "O", "O", "O", "O", "B-ARG1", "I-ARG1", "I-ARG1", "I-ARG1", "I-ARG1", "I-ARG1", "I-ARG1", "B-ARGM-MOD", "O", "B-V", "B-ARG4", "I-ARG4", "I-ARG4", "I-ARG4", "B-ARGM-PRP", "I-ARGM-PRP", "I-ARGM-PRP", "O", "O", "O", "O", "O", "O", "O", "O", "O", "O", "O", "O", "O", "O", "O"]}, {"verb": "meet", "description": "Donald Trump \u2019s fee fees got hurt after the Philadelphia Eagles informed him that [ARG0: only a few representatives of the club] would be coming to the White House to [V: meet] [ARG1: him] . Trump processed this information maturely and decided to publicly un - invite the ...", "tags": ["O", "O", "O", "O", "O", "O", "O", "O", "O", "O", "O", "O", "O", "O", "B-ARG0", "I-ARG0", "I-ARG0", "I-ARG0", "I-ARG0", "I-ARG0", "I-ARG0", "O", "O", "O", "O", "O", "O", "O", "O", "B-V", "B-ARG1", "O", "O", "O", "O", "O", "O", "O", "O", "O", "O", "O", "O", "O", "O", "O"]}, {"verb": "processed", "description": "Donald Trump \u2019s fee fees got hurt after the Philadelphia Eagles informed him that only a few representatives of the club would be coming to the White House to meet him . [ARG0: Trump] [V: processed] [ARG1: this information] [ARGM-MNR: maturely] and decided to publicly un - invite the ...", "tags": ["O", "O", "O", "O", "O", "O", "O", "O", "O", "O", "O", "O", "O", "O", "O", "O", "O", "O", "O", "O", "O", "O", "O", "O", "O", "O", "O", "O", "O", "O", "O", "O", "B-ARG0", "B-V", "B-ARG1", "I-ARG1", "B-ARGM-MNR", "O", "O", "O", "O", "O", "O", "O", "O", "O"]}, {"verb": "decided", "description": "Donald Trump \u2019s fee fees got hurt after the Philadelphia Eagles informed him that only a few representatives of the club would be coming to the White House to meet him . [ARG0: Trump] processed this information maturely and [V: decided] [ARG1: to publicly un - invite the] ...", "tags": ["O", "O", "O", "O", "O", "O", "O", "O", "O", "O", "O", "O", "O", "O", "O", "O", "O", "O", "O", "O", "O", "O", "O", "O", "O", "O", "O", "O", "O", "O", "O", "O", "B-ARG0", "O", "O", "O", "O", "O", "B-V", "B-ARG1", "I-ARG1", "I-ARG1", "I-ARG1", "I-ARG1", "I-ARG1", "O"]}, {"verb": "un", "description": "Donald Trump \u2019s fee fees got hurt after the Philadelphia Eagles informed him that only a few representatives of the club would be coming to the White House to meet him . [ARG0: Trump] processed this information maturely and decided to [ARGM-MNR: publicly] [V: un] - invite [ARG1: the] ...", "tags": ["O", "O", "O", "O", "O", "O", "O", "O", "O", "O", "O", "O", "O", "O", "O", "O", "O", "O", "O", "O", "O", "O", "O", "O", "O", "O", "O", "O", "O", "O", "O", "O", "B-ARG0", "O", "O", "O", "O", "O", "O", "O", "B-ARGM-MNR", "B-V", "O", "O", "B-ARG1", "O"]}, {"verb": "invite", "description": "Donald Trump \u2019s fee fees got hurt after the Philadelphia Eagles informed him that only a few representatives of the club would be coming to the White House to meet him . [ARG0: Trump] processed this information maturely and decided to [ARGM-MNR: publicly] [ARGM-MNR: un -] [V: invite] [ARG1: the] ...", "tags": ["O", "O", "O", "O", "O", "O", "O", "O", "O", "O", "O", "O", "O", "O", "O", "O", "O", "O", "O", "O", "O", "O", "O", "O", "O", "O", "O", "O", "O", "O", "O", "O", "B-ARG0", "O", "O", "O", "O", "O", "O", "O", "B-ARGM-MNR", "B-ARGM-MNR", "I-ARGM-MNR", "B-V", "B-ARG1", "O"]}], "words": ["Donald", "Trump", "\u2019s", "fee", "fees", "got", "hurt", "after", "the", "Philadelphia", "Eagles", "informed", "him", "that", "only", "a", "few", "representatives", "of", "the", "club", "would", "be", "coming", "to", "the", "White", "House", "to", "meet", "him", ".", "Trump", "processed", "this", "information", "maturely", "and", "decided", "to", "publicly", "un", "-", "invite", "the", "..."]}