{"verbs": [{"verb": "was", "description": "After Ivanka Trump [V: was] roasted on Twitter for posting a photo of herself holding her son \u2013 while her father \u2019s policies have separated more than 700 children from their adult caregivers \u2013 Fox News conservatives sprang into Republican Rehab action .", "tags": ["O", "O", "O", "B-V", "O", "O", "O", "O", "O", "O", "O", "O", "O", "O", "O", "O", "O", "O", "O", "O", "O", "O", "O", "O", "O", "O", "O", "O", "O", "O", "O", "O", "O", "O", "O", "O", "O", "O", "O", "O", "O", "O"]}, {"verb": "roasted", "description": "After [ARG1: Ivanka Trump] was [V: roasted] [ARGM-LOC: on Twitter] [ARGM-CAU: for posting a photo of herself holding her son \u2013 while her father \u2019s policies have separated more than 700 children from their adult caregivers] \u2013 Fox News conservatives sprang into Republican Rehab action .", "tags": ["O", "B-ARG1", "I-ARG1", "O", "B-V", "B-ARGM-LOC", "I-ARGM-LOC", "B-ARGM-CAU", "I-ARGM-CAU", "I-ARGM-CAU", "I-ARGM-CAU", "I-ARGM-CAU", "I-ARGM-CAU", "I-ARGM-CAU", "I-ARGM-CAU", "I-ARGM-CAU", "I-ARGM-CAU", "I-ARGM-CAU", "I-ARGM-CAU", "I-ARGM-CAU", "I-ARGM-CAU", "I-ARGM-CAU", "I-ARGM-CAU", "I-ARGM-CAU", "I-ARGM-CAU", "I-ARGM-CAU", "I-ARGM-CAU", "I-ARGM-CAU", "I-ARGM-CAU", "I-ARGM-CAU", "I-ARGM-CAU", "I-ARGM-CAU", "O", "O", "O", "O", "O", "O", "O", "O", "O", "O"]}, {"verb": "posting", "description": "After [ARG0: Ivanka Trump] was roasted on Twitter for [V: posting] [ARG1: a photo of herself holding her son] \u2013 [ARGM-ADV: while her father \u2019s policies have separated more than 700 children from their adult caregivers] \u2013 Fox News conservatives sprang into Republican Rehab action .", "tags": ["O", "B-ARG0", "I-ARG0", "O", "O", "O", "O", "O", "B-V", "B-ARG1", "I-ARG1", "I-ARG1", "I-ARG1", "I-ARG1", "I-ARG1", "I-ARG1", "O", "B-ARGM-ADV", "I-ARGM-ADV", "I-ARGM-ADV", "I-ARGM-ADV", "I-ARGM-ADV", "I-ARGM-ADV", "I-ARGM-ADV", "I-ARGM-ADV", "I-ARGM-ADV", "I-ARGM-ADV", "I-ARGM-ADV", "I-ARGM-ADV", "I-ARGM-ADV", "I-ARGM-ADV", "I-ARGM-ADV", "O", "O", "O", "O", "O", "O", "O", "O", "O", "O"]}, {"verb": "holding", "description": "After Ivanka Trump was roasted on Twitter for posting a photo of [ARG0: herself] [V: holding] [ARG1: her son] \u2013 while her father \u2019s policies have separated more than 700 children from their adult caregivers \u2013 Fox News conservatives sprang into Republican Rehab action .", "tags": ["O", "O", "O", "O", "O", "O", "O", "O", "O", "O", "O", "O", "B-ARG0", "B-V", "B-ARG1", "I-ARG1", "O", "O", "O", "O", "O", "O", "O", "O", "O", "O", "O", "O", "O", "O", "O", "O", "O", "O", "O", "O", "O", "O", "O", "O", "O", "O"]}, {"verb": "have", "description": "After Ivanka Trump was roasted on Twitter for posting a photo of herself holding her son \u2013 while her father \u2019s policies [V: have] separated more than 700 children from their adult caregivers \u2013 Fox News conservatives sprang into Republican Rehab action .", "tags": ["O", "O", "O", "O", "O", "O", "O", "O", "O", "O", "O", "O", "O", "O", "O", "O", "O", "O", "O", "O", "O", "O", "B-V", "O", "O", "O", "O", "O", "O", "O", "O", "O", "O", "O", "O", "O", "O", "O", "O", "O", "O", "O"]}, {"verb": "separated", "description": "After Ivanka Trump was roasted on Twitter for posting a photo of herself holding her son \u2013 while [ARG0: her father \u2019s policies] have [V: separated] [ARG1: more than 700 children] [ARG2: from their adult caregivers] \u2013 Fox News conservatives sprang into Republican Rehab action .", "tags": ["O", "O", "O", "O", "O", "O", "O", "O", "O", "O", "O", "O", "O", "O", "O", "O", "O", "O", "B-ARG0", "I-ARG0", "I-ARG0", "I-ARG0", "O", "B-V", "B-ARG1", "I-ARG1", "I-ARG1", "I-ARG1", "B-ARG2", "I-ARG2", "I-ARG2", "I-ARG2", "O", "O", "O", "O", "O", "O", "O", "O", "O", "O"]}, {"verb": "sprang", "description": "[ARGM-TMP: After Ivanka Trump was roasted on Twitter for posting a photo of herself holding her son \u2013 while her father \u2019s policies have separated more than 700 children from their adult caregivers \u2013] [ARG1: Fox News conservatives] [V: sprang] [ARG2: into Republican Rehab action] .", "tags": ["B-ARGM-TMP", "I-ARGM-TMP", "I-ARGM-TMP", "I-ARGM-TMP", "I-ARGM-TMP", "I-ARGM-TMP", "I-ARGM-TMP", "I-ARGM-TMP", "I-ARGM-TMP", "I-ARGM-TMP", "I-ARGM-TMP", "I-ARGM-TMP", "I-ARGM-TMP", "I-ARGM-TMP", "I-ARGM-TMP", "I-ARGM-TMP", "I-ARGM-TMP", "I-ARGM-TMP", "I-ARGM-TMP", "I-ARGM-TMP", "I-ARGM-TMP", "I-ARGM-TMP", "I-ARGM-TMP", "I-ARGM-TMP", "I-ARGM-TMP", "I-ARGM-TMP", "I-ARGM-TMP", "I-ARGM-TMP", "I-ARGM-TMP", "I-ARGM-TMP", "I-ARGM-TMP", "I-ARGM-TMP", "I-ARGM-TMP", "B-ARG1", "I-ARG1", "I-ARG1", "B-V", "B-ARG2", "I-ARG2", "I-ARG2", "I-ARG2", "O"]}], "words": ["After", "Ivanka", "Trump", "was", "roasted", "on", "Twitter", "for", "posting", "a", "photo", "of", "herself", "holding", "her", "son", "\u2013", "while", "her", "father", "\u2019s", "policies", "have", "separated", "more", "than", "700", "children", "from", "their", "adult", "caregivers", "\u2013", "Fox", "News", "conservatives", "sprang", "into", "Republican", "Rehab", "action", "."]}