{"verbs": [{"verb": "heads", "description": "[ARG0: Rep. Steve Stivers] , [R-ARG0: who] [V: heads] [ARG1: the GOP House campaign committee] , challenges President Trump to stop separating children from their parents at the border", "tags": ["B-ARG0", "I-ARG0", "I-ARG0", "O", "B-R-ARG0", "B-V", "B-ARG1", "I-ARG1", "I-ARG1", "I-ARG1", "I-ARG1", "O", "O", "O", "O", "O", "O", "O", "O", "O", "O", "O", "O", "O", "O"]}, {"verb": "challenges", "description": "[ARG0: Rep. Steve Stivers , who heads the GOP House campaign committee ,] [V: challenges] [ARG1: President Trump] [ARG2: to stop separating children from their parents at the border]", "tags": ["B-ARG0", "I-ARG0", "I-ARG0", "I-ARG0", "I-ARG0", "I-ARG0", "I-ARG0", "I-ARG0", "I-ARG0", "I-ARG0", "I-ARG0", "I-ARG0", "B-V", "B-ARG1", "I-ARG1", "B-ARG2", "I-ARG2", "I-ARG2", "I-ARG2", "I-ARG2", "I-ARG2", "I-ARG2", "I-ARG2", "I-ARG2", "I-ARG2"]}, {"verb": "stop", "description": "Rep. Steve Stivers , who heads the GOP House campaign committee , challenges [ARG0: President Trump] to [V: stop] [ARG1: separating children from their parents at the border]", "tags": ["O", "O", "O", "O", "O", "O", "O", "O", "O", "O", "O", "O", "O", "B-ARG0", "I-ARG0", "O", "B-V", "B-ARG1", "I-ARG1", "I-ARG1", "I-ARG1", "I-ARG1", "I-ARG1", "I-ARG1", "I-ARG1"]}, {"verb": "separating", "description": "Rep. Steve Stivers , who heads the GOP House campaign committee , challenges [ARG0: President Trump] to stop [V: separating] [ARG1: children] [ARG2: from their parents] [ARGM-LOC: at the border]", "tags": ["O", "O", "O", "O", "O", "O", "O", "O", "O", "O", "O", "O", "O", "B-ARG0", "I-ARG0", "O", "O", "B-V", "B-ARG1", "B-ARG2", "I-ARG2", "I-ARG2", "B-ARGM-LOC", "I-ARGM-LOC", "I-ARGM-LOC"]}], "words": ["Rep.", "Steve", "Stivers", ",", "who", "heads", "the", "GOP", "House", "campaign", "committee", ",", "challenges", "President", "Trump", "to", "stop", "separating", "children", "from", "their", "parents", "at", "the", "border"]}