{"verbs": [{"verb": "jumped", "description": "[ARG0: Iowa Republican delegates] [V: jumped] [ARGM-DIR: to their feet] [ARGM-TMP: when asked to show if they support President Trump] . \" Do you hear it ? We 're united ! \" chairman exulted .", "tags": ["B-ARG0", "I-ARG0", "I-ARG0", "B-V", "B-ARGM-DIR", "I-ARGM-DIR", "I-ARGM-DIR", "B-ARGM-TMP", "I-ARGM-TMP", "I-ARGM-TMP", "I-ARGM-TMP", "I-ARGM-TMP", "I-ARGM-TMP", "I-ARGM-TMP", "I-ARGM-TMP", "I-ARGM-TMP", "O", "O", "O", "O", "O", "O", "O", "O", "O", "O", "O", "O", "O", "O", "O"]}, {"verb": "asked", "description": "[ARG2: Iowa Republican delegates] jumped to their feet [ARGM-TMP: when] [V: asked] [ARG1: to show if they support President Trump] . \" Do you hear it ? We 're united ! \" chairman exulted .", "tags": ["B-ARG2", "I-ARG2", "I-ARG2", "O", "O", "O", "O", "B-ARGM-TMP", "B-V", "B-ARG1", "I-ARG1", "I-ARG1", "I-ARG1", "I-ARG1", "I-ARG1", "I-ARG1", "O", "O", "O", "O", "O", "O", "O", "O", "O", "O", "O", "O", "O", "O", "O"]}, {"verb": "show", "description": "[ARG0: Iowa Republican delegates] jumped to their feet when asked to [V: show] [ARG1: if they support President Trump] . \" Do you hear it ? We 're united ! \" chairman exulted .", "tags": ["B-ARG0", "I-ARG0", "I-ARG0", "O", "O", "O", "O", "O", "O", "O", "B-V", "B-ARG1", "I-ARG1", "I-ARG1", "I-ARG1", "I-ARG1", "O", "O", "O", "O", "O", "O", "O", "O", "O", "O", "O", "O", "O", "O", "O"]}, {"verb": "support", "description": "Iowa Republican delegates jumped to their feet when asked to show if [ARG0: they] [V: support] [ARG1: President Trump] . \" Do you hear it ? We 're united ! \" chairman exulted .", "tags": ["O", "O", "O", "O", "O", "O", "O", "O", "O", "O", "O", "O", "B-ARG0", "B-V", "B-ARG1", "I-ARG1", "O", "O", "O", "O", "O", "O", "O", "O", "O", "O", "O", "O", "O", "O", "O"]}, {"verb": "Do", "description": "Iowa Republican delegates jumped to their feet when asked to show if they support President Trump . \" [V: Do] you hear it ? We 're united ! \" chairman exulted .", "tags": ["O", "O", "O", "O", "O", "O", "O", "O", "O", "O", "O", "O", "O", "O", "O", "O", "O", "O", "B-V", "O", "O", "O", "O", "O", "O", "O", "O", "O", "O", "O", "O"]}, {"verb": "hear", "description": "Iowa Republican delegates jumped to their feet when asked to show if they support President Trump . \" Do [ARG0: you] [V: hear] [ARG1: it] ? We 're united ! \" chairman exulted .", "tags": ["O", "O", "O", "O", "O", "O", "O", "O", "O", "O", "O", "O", "O", "O", "O", "O", "O", "O", "O", "B-ARG0", "B-V", "B-ARG1", "O", "O", "O", "O", "O", "O", "O", "O", "O"]}, {"verb": "'re", "description": "Iowa Republican delegates jumped to their feet when asked to show if they support President Trump . \" Do you hear it ? [ARG1: We] [V: 're] [ARG2: united] ! \" chairman exulted .", "tags": ["O", "O", "O", "O", "O", "O", "O", "O", "O", "O", "O", "O", "O", "O", "O", "O", "O", "O", "O", "O", "O", "O", "O", "B-ARG1", "B-V", "B-ARG2", "O", "O", "O", "O", "O"]}, {"verb": "exulted", "description": "[ARG1: Iowa Republican delegates jumped to their feet when asked to show if they support President Trump . \" Do you hear it ? We 're united ! \"] [ARG0: chairman] [V: exulted] .", "tags": ["B-ARG1", "I-ARG1", "I-ARG1", "I-ARG1", "I-ARG1", "I-ARG1", "I-ARG1", "I-ARG1", "I-ARG1", "I-ARG1", "I-ARG1", "I-ARG1", "I-ARG1", "I-ARG1", "I-ARG1", "I-ARG1", "I-ARG1", "I-ARG1", "I-ARG1", "I-ARG1", "I-ARG1", "I-ARG1", "I-ARG1", "I-ARG1", "I-ARG1", "I-ARG1", "I-ARG1", "I-ARG1", "B-ARG0", "B-V", "O"]}], "words": ["Iowa", "Republican", "delegates", "jumped", "to", "their", "feet", "when", "asked", "to", "show", "if", "they", "support", "President", "Trump", ".", "\"", "Do", "you", "hear", "it", "?", "We", "'re", "united", "!", "\"", "chairman", "exulted", "."]}